{
  "generatedAt": "2026-06-29T08:23:23.899Z",
  "label": "after-landing-fonts",
  "budgetMs": 50,
  "iterations": 7,
  "warmups": 3,
  "skipBuild": false,
  "browserExecutable": "/Applications/Google Chrome.app/Contents/MacOS/Google Chrome",
  "summary": [
    {
      "id": "landing.home",
      "app": "landing",
      "type": "url",
      "samples": 7,
      "minMs": 54.2,
      "p50Ms": 55.1,
      "p95Ms": 55.7,
      "maxMs": 55.7,
      "meanMs": 55.2,
      "pass": false
    },
    {
      "id": "landing.login",
      "app": "landing",
      "type": "url",
      "samples": 7,
      "minMs": 46.7,
      "p50Ms": 47.5,
      "p95Ms": 48.3,
      "maxMs": 48.3,
      "meanMs": 47.5,
      "pass": true
    },
    {
      "id": "landing.register",
      "app": "landing",
      "type": "url",
      "samples": 7,
      "minMs": 45.4,
      "p50Ms": 47,
      "p95Ms": 62,
      "maxMs": 62,
      "meanMs": 48.9,
      "pass": false
    },
    {
      "id": "landing.register-passkey",
      "app": "landing",
      "type": "url",
      "samples": 7,
      "minMs": 44.9,
      "p50Ms": 45.6,
      "p95Ms": 47.3,
      "maxMs": 47.3,
      "meanMs": 45.7,
      "pass": true
    },
    {
      "id": "landing.privacy",
      "app": "landing",
      "type": "url",
      "samples": 7,
      "minMs": 46.4,
      "p50Ms": 47.7,
      "p95Ms": 48.9,
      "maxMs": 48.9,
      "meanMs": 47.8,
      "pass": true
    }
  ],
  "details": [
    {
      "id": "landing.home",
      "app": "landing",
      "type": "url",
      "url": "http://127.0.0.1:5173/",
      "samples": [
        {
          "durationMs": 54.2,
          "domContentLoadedMs": 40,
          "loadEventMs": 43,
          "responseStartMs": 35,
          "firstPaintMs": null,
          "firstContentfulPaintMs": null,
          "transferSize": 300,
          "encodedBodySize": 8894,
          "wallClockMs": 55.9,
          "warmup": false,
          "consoleErrorCount": 0,
          "consoleErrors": []
        },
        {
          "durationMs": 55.1,
          "domContentLoadedMs": 41,
          "loadEventMs": 49,
          "responseStartMs": 35,
          "firstPaintMs": null,
          "firstContentfulPaintMs": null,
          "transferSize": 300,
          "encodedBodySize": 8894,
          "wallClockMs": 56.9,
          "warmup": false,
          "consoleErrorCount": 0,
          "consoleErrors": []
        },
        {
          "durationMs": 54.9,
          "domContentLoadedMs": 41,
          "loadEventMs": 43,
          "responseStartMs": 35,
          "firstPaintMs": null,
          "firstContentfulPaintMs": null,
          "transferSize": 300,
          "encodedBodySize": 8894,
          "wallClockMs": 56.8,
          "warmup": false,
          "consoleErrorCount": 0,
          "consoleErrors": []
        },
        {
          "durationMs": 55.7,
          "domContentLoadedMs": 41,
          "loadEventMs": 43,
          "responseStartMs": 34,
          "firstPaintMs": null,
          "firstContentfulPaintMs": null,
          "transferSize": 300,
          "encodedBodySize": 8894,
          "wallClockMs": 57.3,
          "warmup": false,
          "consoleErrorCount": 0,
          "consoleErrors": []
        },
        {
          "durationMs": 55.6,
          "domContentLoadedMs": 40,
          "loadEventMs": 43,
          "responseStartMs": 35,
          "firstPaintMs": null,
          "firstContentfulPaintMs": null,
          "transferSize": 300,
          "encodedBodySize": 8894,
          "wallClockMs": 57.3,
          "warmup": false,
          "consoleErrorCount": 0,
          "consoleErrors": []
        },
        {
          "durationMs": 55.6,
          "domContentLoadedMs": 41,
          "loadEventMs": 44,
          "responseStartMs": 35,
          "firstPaintMs": null,
          "firstContentfulPaintMs": null,
          "transferSize": 300,
          "encodedBodySize": 8894,
          "wallClockMs": 57.4,
          "warmup": false,
          "consoleErrorCount": 0,
          "consoleErrors": []
        },
        {
          "durationMs": 55.1,
          "domContentLoadedMs": 41,
          "loadEventMs": 43,
          "responseStartMs": 35,
          "firstPaintMs": null,
          "firstContentfulPaintMs": null,
          "transferSize": 300,
          "encodedBodySize": 8894,
          "wallClockMs": 57.1,
          "warmup": false,
          "consoleErrorCount": 0,
          "consoleErrors": []
        }
      ]
    },
    {
      "id": "landing.login",
      "app": "landing",
      "type": "url",
      "url": "http://127.0.0.1:5173/login",
      "samples": [
        {
          "durationMs": 47.5,
          "domContentLoadedMs": 39,
          "loadEventMs": 41,
          "responseStartMs": 34,
          "firstPaintMs": null,
          "firstContentfulPaintMs": null,
          "transferSize": 300,
          "encodedBodySize": 1872,
          "wallClockMs": 49,
          "warmup": false,
          "consoleErrorCount": 0,
          "consoleErrors": []
        },
        {
          "durationMs": 48.3,
          "domContentLoadedMs": 39,
          "loadEventMs": 40,
          "responseStartMs": 34,
          "firstPaintMs": null,
          "firstContentfulPaintMs": null,
          "transferSize": 300,
          "encodedBodySize": 1872,
          "wallClockMs": 50.1,
          "warmup": false,
          "consoleErrorCount": 0,
          "consoleErrors": []
        },
        {
          "durationMs": 47.9,
          "domContentLoadedMs": 39,
          "loadEventMs": 40,
          "responseStartMs": 34,
          "firstPaintMs": null,
          "firstContentfulPaintMs": null,
          "transferSize": 300,
          "encodedBodySize": 1872,
          "wallClockMs": 49.5,
          "warmup": false,
          "consoleErrorCount": 0,
          "consoleErrors": []
        },
        {
          "durationMs": 47.3,
          "domContentLoadedMs": 39,
          "loadEventMs": 40,
          "responseStartMs": 34,
          "firstPaintMs": null,
          "firstContentfulPaintMs": null,
          "transferSize": 300,
          "encodedBodySize": 1872,
          "wallClockMs": 49.1,
          "warmup": false,
          "consoleErrorCount": 0,
          "consoleErrors": []
        },
        {
          "durationMs": 47.7,
          "domContentLoadedMs": 38,
          "loadEventMs": 40,
          "responseStartMs": 34,
          "firstPaintMs": null,
          "firstContentfulPaintMs": null,
          "transferSize": 300,
          "encodedBodySize": 1872,
          "wallClockMs": 49.4,
          "warmup": false,
          "consoleErrorCount": 0,
          "consoleErrors": []
        },
        {
          "durationMs": 47.2,
          "domContentLoadedMs": 39,
          "loadEventMs": 40,
          "responseStartMs": 34,
          "firstPaintMs": null,
          "firstContentfulPaintMs": null,
          "transferSize": 300,
          "encodedBodySize": 1872,
          "wallClockMs": 48.7,
          "warmup": false,
          "consoleErrorCount": 0,
          "consoleErrors": []
        },
        {
          "durationMs": 46.7,
          "domContentLoadedMs": 38,
          "loadEventMs": 40,
          "responseStartMs": 34,
          "firstPaintMs": null,
          "firstContentfulPaintMs": null,
          "transferSize": 300,
          "encodedBodySize": 1872,
          "wallClockMs": 48.1,
          "warmup": false,
          "consoleErrorCount": 0,
          "consoleErrors": []
        }
      ]
    },
    {
      "id": "landing.register",
      "app": "landing",
      "type": "url",
      "url": "http://127.0.0.1:5173/register",
      "samples": [
        {
          "durationMs": 62,
          "domContentLoadedMs": 53,
          "loadEventMs": 54,
          "responseStartMs": 48,
          "firstPaintMs": null,
          "firstContentfulPaintMs": null,
          "transferSize": 300,
          "encodedBodySize": 1715,
          "wallClockMs": 63.6,
          "warmup": false,
          "consoleErrorCount": 0,
          "consoleErrors": []
        },
        {
          "durationMs": 47.2,
          "domContentLoadedMs": 38,
          "loadEventMs": 39,
          "responseStartMs": 33,
          "firstPaintMs": null,
          "firstContentfulPaintMs": null,
          "transferSize": 300,
          "encodedBodySize": 1715,
          "wallClockMs": 48.9,
          "warmup": false,
          "consoleErrorCount": 0,
          "consoleErrors": []
        },
        {
          "durationMs": 47,
          "domContentLoadedMs": 38,
          "loadEventMs": 39,
          "responseStartMs": 33,
          "firstPaintMs": null,
          "firstContentfulPaintMs": null,
          "transferSize": 300,
          "encodedBodySize": 1715,
          "wallClockMs": 48.5,
          "warmup": false,
          "consoleErrorCount": 0,
          "consoleErrors": []
        },
        {
          "durationMs": 46.2,
          "domContentLoadedMs": 38,
          "loadEventMs": 39,
          "responseStartMs": 33,
          "firstPaintMs": null,
          "firstContentfulPaintMs": null,
          "transferSize": 300,
          "encodedBodySize": 1715,
          "wallClockMs": 48.1,
          "warmup": false,
          "consoleErrorCount": 0,
          "consoleErrors": []
        },
        {
          "durationMs": 45.4,
          "domContentLoadedMs": 37,
          "loadEventMs": 38,
          "responseStartMs": 32,
          "firstPaintMs": null,
          "firstContentfulPaintMs": null,
          "transferSize": 300,
          "encodedBodySize": 1715,
          "wallClockMs": 47,
          "warmup": false,
          "consoleErrorCount": 0,
          "consoleErrors": []
        },
        {
          "durationMs": 48.2,
          "domContentLoadedMs": 38,
          "loadEventMs": 40,
          "responseStartMs": 33,
          "firstPaintMs": null,
          "firstContentfulPaintMs": null,
          "transferSize": 300,
          "encodedBodySize": 1715,
          "wallClockMs": 49.8,
          "warmup": false,
          "consoleErrorCount": 0,
          "consoleErrors": []
        },
        {
          "durationMs": 46.2,
          "domContentLoadedMs": 38,
          "loadEventMs": 39,
          "responseStartMs": 33,
          "firstPaintMs": null,
          "firstContentfulPaintMs": null,
          "transferSize": 300,
          "encodedBodySize": 1715,
          "wallClockMs": 47.7,
          "warmup": false,
          "consoleErrorCount": 0,
          "consoleErrors": []
        }
      ]
    },
    {
      "id": "landing.register-passkey",
      "app": "landing",
      "type": "url",
      "url": "http://127.0.0.1:5173/register/passkey",
      "samples": [
        {
          "durationMs": 45.9,
          "domContentLoadedMs": 38,
          "loadEventMs": 38,
          "responseStartMs": 33,
          "firstPaintMs": null,
          "firstContentfulPaintMs": null,
          "transferSize": 300,
          "encodedBodySize": 1523,
          "wallClockMs": 47.5,
          "warmup": false,
          "consoleErrorCount": 0,
          "consoleErrors": []
        },
        {
          "durationMs": 44.9,
          "domContentLoadedMs": 37,
          "loadEventMs": 38,
          "responseStartMs": 33,
          "firstPaintMs": null,
          "firstContentfulPaintMs": null,
          "transferSize": 300,
          "encodedBodySize": 1523,
          "wallClockMs": 46.5,
          "warmup": false,
          "consoleErrorCount": 0,
          "consoleErrors": []
        },
        {
          "durationMs": 47.3,
          "domContentLoadedMs": 38,
          "loadEventMs": 38,
          "responseStartMs": 33,
          "firstPaintMs": null,
          "firstContentfulPaintMs": null,
          "transferSize": 300,
          "encodedBodySize": 1523,
          "wallClockMs": 48.9,
          "warmup": false,
          "consoleErrorCount": 0,
          "consoleErrors": []
        },
        {
          "durationMs": 45.3,
          "domContentLoadedMs": 38,
          "loadEventMs": 38,
          "responseStartMs": 33,
          "firstPaintMs": null,
          "firstContentfulPaintMs": null,
          "transferSize": 300,
          "encodedBodySize": 1523,
          "wallClockMs": 47,
          "warmup": false,
          "consoleErrorCount": 0,
          "consoleErrors": []
        },
        {
          "durationMs": 45.6,
          "domContentLoadedMs": 38,
          "loadEventMs": 38,
          "responseStartMs": 33,
          "firstPaintMs": null,
          "firstContentfulPaintMs": null,
          "transferSize": 300,
          "encodedBodySize": 1523,
          "wallClockMs": 47.5,
          "warmup": false,
          "consoleErrorCount": 0,
          "consoleErrors": []
        },
        {
          "durationMs": 45.1,
          "domContentLoadedMs": 38,
          "loadEventMs": 38,
          "responseStartMs": 33,
          "firstPaintMs": null,
          "firstContentfulPaintMs": null,
          "transferSize": 300,
          "encodedBodySize": 1523,
          "wallClockMs": 46.5,
          "warmup": false,
          "consoleErrorCount": 0,
          "consoleErrors": []
        },
        {
          "durationMs": 45.6,
          "domContentLoadedMs": 38,
          "loadEventMs": 38,
          "responseStartMs": 33,
          "firstPaintMs": null,
          "firstContentfulPaintMs": null,
          "transferSize": 300,
          "encodedBodySize": 1523,
          "wallClockMs": 47.1,
          "warmup": false,
          "consoleErrorCount": 0,
          "consoleErrors": []
        }
      ]
    },
    {
      "id": "landing.privacy",
      "app": "landing",
      "type": "url",
      "url": "http://127.0.0.1:5173/privacy",
      "samples": [
        {
          "durationMs": 46.4,
          "domContentLoadedMs": 37,
          "loadEventMs": 38,
          "responseStartMs": 33,
          "firstPaintMs": null,
          "firstContentfulPaintMs": null,
          "transferSize": 300,
          "encodedBodySize": 3887,
          "wallClockMs": 48.6,
          "warmup": false,
          "consoleErrorCount": 0,
          "consoleErrors": []
        },
        {
          "durationMs": 47.7,
          "domContentLoadedMs": 38,
          "loadEventMs": 38,
          "responseStartMs": 33,
          "firstPaintMs": null,
          "firstContentfulPaintMs": null,
          "transferSize": 300,
          "encodedBodySize": 3887,
          "wallClockMs": 49.3,
          "warmup": false,
          "consoleErrorCount": 0,
          "consoleErrors": []
        },
        {
          "durationMs": 48.6,
          "domContentLoadedMs": 39,
          "loadEventMs": 40,
          "responseStartMs": 35,
          "firstPaintMs": null,
          "firstContentfulPaintMs": null,
          "transferSize": 300,
          "encodedBodySize": 3887,
          "wallClockMs": 50.5,
          "warmup": false,
          "consoleErrorCount": 0,
          "consoleErrors": []
        },
        {
          "durationMs": 47.7,
          "domContentLoadedMs": 39,
          "loadEventMs": 39,
          "responseStartMs": 33,
          "firstPaintMs": null,
          "firstContentfulPaintMs": null,
          "transferSize": 300,
          "encodedBodySize": 3887,
          "wallClockMs": 49.4,
          "warmup": false,
          "consoleErrorCount": 0,
          "consoleErrors": []
        },
        {
          "durationMs": 48.9,
          "domContentLoadedMs": 39,
          "loadEventMs": 39,
          "responseStartMs": 34,
          "firstPaintMs": null,
          "firstContentfulPaintMs": null,
          "transferSize": 300,
          "encodedBodySize": 3887,
          "wallClockMs": 50.5,
          "warmup": false,
          "consoleErrorCount": 0,
          "consoleErrors": []
        },
        {
          "durationMs": 47.6,
          "domContentLoadedMs": 38,
          "loadEventMs": 39,
          "responseStartMs": 33,
          "firstPaintMs": null,
          "firstContentfulPaintMs": null,
          "transferSize": 300,
          "encodedBodySize": 3887,
          "wallClockMs": 49.1,
          "warmup": false,
          "consoleErrorCount": 0,
          "consoleErrors": []
        },
        {
          "durationMs": 47.8,
          "domContentLoadedMs": 38,
          "loadEventMs": 39,
          "responseStartMs": 33,
          "firstPaintMs": null,
          "firstContentfulPaintMs": null,
          "transferSize": 300,
          "encodedBodySize": 3887,
          "wallClockMs": 49.4,
          "warmup": false,
          "consoleErrorCount": 0,
          "consoleErrors": []
        }
      ]
    }
  ]
}